danielduchouquette/__init__.py
danielduchouquette/add.py
danielduchouquette/subtract.py
danielduchouquette-3.10.0.dist-info/METADATA
danielduchouquette-3.10.0.dist-info/WHEEL
danielduchouquette-3.10.0.dist-info/top_level.txt
danielduchouquette-3.10.0.dist-info/RECORD
